{
  "$schema": "https://json-schema.org/draft/2020-12/schema",
  "$id": "https://raw.githubusercontent.com/api-evangelist/adobe-experience-cloud/refs/heads/main/json-schema/journey-optimizer-api-placement-list-schema.json",
  "title": "PlacementList",
  "description": "PlacementList schema",
  "type": "object",
  "properties": {
    "placements": {
      "type": "array",
      "items": {
        "type": "object",
        "properties": {
          "id": {
            "type": "string"
          },
          "name": {
            "type": "string"
          },
          "channel": {
            "type": "string"
          },
          "contentType": {
            "type": "string"
          }
        }
      }
    }
  }
}